{
  "Frame": [
    {
      "NAME": "NOSE",
      "x": 0.0,
      "y": 0.0,
      "score": 0.0
    },
    {
      "NAME": "LEFT_EYE",
      "x": 0.0,
      "y": 0.0,
      "score": 0.0
    },
    {
      "NAME": "RIGHT_EYE",
      "x": 0.0,
      "y": 0.0,
      "score": 0.0
    },
    {
      "NAME": "LEFT_EAR",
      "x": 0.0,
      "y": 0.0,
      "score": 0.0
    },
    {
      "NAME": "RIGHT_EAR",
      "x": 0.0,
      "y": 0.0,
      "score": 0.0
    },
    {
      "NAME": "LEFT_SHOULDER",
      "x": 1094.7757568359375,
      "y": 341.8804016113281,
      "score": 0.33141931891441345
    },
    {
      "NAME": "RIGHT_SHOULDER",
      "x": 972.9866943359375,
      "y": 284.98614501953125,
      "score": 0.7072309255599976
    },
    {
      "NAME": "LEFT_ELBOW",
      "x": 0.0,
      "y": 0.0,
      "score": 0.0
    },
    {
      "NAME": "RIGHT_ELBOW",
      "x": 880.5413208007812,
      "y": 380.1624450683594,
      "score": 0.6339236497879028
    },
    {
      "NAME": "LEFT_WRIST",
      "x": 0.0,
      "y": 0.0,
      "score": 0.0
    },
    {
      "NAME": "RIGHT_WRIST",
      "x": 828.5645141601562,
      "y": 509.9407653808594,
      "score": 0.7358859181404114
    },
    {
      "NAME": "LEFT_HIP",
      "x": 1015.5121459960938,
      "y": 574.90966796875,
      "score": 0.6801660656929016
    },
    {
      "NAME": "RIGHT_HIP",
      "x": 912.1417846679688,
      "y": 560.3438110351562,
      "score": 0.964846670627594
    },
    {
      "NAME": "LEFT_KNEE",
      "x": 1031.7786865234375,
      "y": 791.4574584960938,
      "score": 0.5475042462348938
    },
    {
      "NAME": "RIGHT_KNEE",
      "x": 906.9052124023438,
      "y": 790.2302856445312,
      "score": 0.623664915561676
    },
    {
      "NAME": "LEFT_ANKLE",
      "x": 1028.530517578125,
      "y": 977.0133056640625,
      "score": 0.6492154598236084
    },
    {
      "NAME": "RIGHT_ANKLE",
      "x": 918.0711669921875,
      "y": 976.9461669921875,
      "score": 0.7053991556167603
    }
  ]
}