{
  "Frame": [
    {
      "NAME": "NOSE",
      "x": 1077.6842041015625,
      "y": 199.4762420654297,
      "score": 0.8982933163642883
    },
    {
      "NAME": "LEFT_EYE",
      "x": 1101.391357421875,
      "y": 186.2698211669922,
      "score": 1.0
    },
    {
      "NAME": "RIGHT_EYE",
      "x": 1062.7880859375,
      "y": 173.46786499023438,
      "score": 0.9513666033744812
    },
    {
      "NAME": "LEFT_EAR",
      "x": 1118.790771484375,
      "y": 211.3726043701172,
      "score": 0.8248937726020813
    },
    {
      "NAME": "RIGHT_EAR",
      "x": 1029.567138671875,
      "y": 180.25711059570312,
      "score": 0.9210065603256226
    },
    {
      "NAME": "LEFT_SHOULDER",
      "x": 1110.41552734375,
      "y": 336.1943359375,
      "score": 0.6559568047523499
    },
    {
      "NAME": "RIGHT_SHOULDER",
      "x": 942.147216796875,
      "y": 279.40594482421875,
      "score": 0.8413802981376648
    },
    {
      "NAME": "LEFT_ELBOW",
      "x": 1124.3111572265625,
      "y": 495.2889709472656,
      "score": 0.4124324321746826
    },
    {
      "NAME": "RIGHT_ELBOW",
      "x": 868.5958251953125,
      "y": 410.4748229980469,
      "score": 0.6931772232055664
    },
    {
      "NAME": "LEFT_WRIST",
      "x": 0.0,
      "y": 0.0,
      "score": 0.0
    },
    {
      "NAME": "RIGHT_WRIST",
      "x": 839.6587524414062,
      "y": 552.7373046875,
      "score": 0.7796571254730225
    },
    {
      "NAME": "LEFT_HIP",
      "x": 1026.0870361328125,
      "y": 574.1106567382812,
      "score": 0.5543750524520874
    },
    {
      "NAME": "RIGHT_HIP",
      "x": 935.2326049804688,
      "y": 540.55712890625,
      "score": 0.5436541438102722
    },
    {
      "NAME": "LEFT_KNEE",
      "x": 1035.270751953125,
      "y": 777.1722412109375,
      "score": 0.4451909065246582
    },
    {
      "NAME": "RIGHT_KNEE",
      "x": 920.1397705078125,
      "y": 771.214599609375,
      "score": 0.3384874165058136
    },
    {
      "NAME": "LEFT_ANKLE",
      "x": 1027.61572265625,
      "y": 979.1165161132812,
      "score": 0.538564145565033
    },
    {
      "NAME": "RIGHT_ANKLE",
      "x": 0.0,
      "y": 0.0,
      "score": 0.0
    }
  ]
}